[
    {
        "code": 1,
        "user_name": "NoaCohen",
        "password": "password123",
        "image": "https://via.placeholder.com/150/0000FF/FFFFFF?text=Noa"
    },
    {
        "code": 2,
        "user_name": "ItiLevi",
        "password": "securepass456",
        "image": "https://via.placeholder.com/150/FF0000/FFFFFF?text=Iti"
    },
    {
        "code": 3,
        "user_name": "MayaRose",
        "password": "mypassword789",
        "image": "https://via.placeholder.com/150/00FF00/FFFFFF?text=Maya"
    },
    {
        "code": 4,
        "user_name": "ShaharBen",
        "password": "pass1234",
        "image": "https://via.placeholder.com/150/FFFF00/FFFFFF?text=Shahar"
    },
    {
        "code": 5,
        "user_name": "TamarBar",
        "password": "hello5678",
        "image": "https://via.placeholder.com/150/FF00FF/FFFFFF?text=Tamar"
    }
]